example_package_avdufour/__init__.py
example_package_avdufour/example.py
example_package_avdufour-0.0.1.dist-info/METADATA
example_package_avdufour-0.0.1.dist-info/WHEEL
example_package_avdufour-0.0.1.dist-info/licenses/LICENSE
example_package_avdufour-0.0.1.dist-info/RECORD
