Metadata-Version: 2.1
Name: example_package_avdufour
Version: 0.0.1
Summary: A small example package
Project-URL: Homepage, https://github.com/pypa/sampleproject
Project-URL: Bug Tracker, https://github.com/pypa/sampleproject/issues
Author-email: Vincent Dufour <avdufour@gmail.com>
License-File: LICENSE
Classifier: License :: OSI Approved :: MIT License
Classifier: Operating System :: OS Independent
Classifier: Programming Language :: Python :: 3
Requires-Python: >=3.7
